radprompter/__init__.py
radprompter/__version__.py
radprompter/radprompter.py
radprompter/clients/__init__.py
radprompter/clients/clients.py
radprompter/clients/huggingface/clients.py
radprompter/clients/openai/clients.py
radprompter/prompts/__init__.py
radprompter/prompts/prompts.py
radprompter-1.1.15.dist-info/LICENSE
radprompter-1.1.15.dist-info/WHEEL
radprompter-1.1.15.dist-info/METADATA
radprompter-1.1.15.dist-info/RECORD
