Metadata-Version: 2.1
Name: radprompter
Version: 1.1.15
Summary: A package for simplified and reproducible LLM prompting.
Author-email: Bardia Khosravi <bardiakhosravi95@gmail.com>, Theo Dapamede <theo.dapamede@emory.edu>
Maintainer-email: Bardia Khosravi <bardiakhosravi95@gmail.com>, Theo Dapamede <theo.dapamede@emory.edu>
Requires-Python: >=3.7
Classifier: License :: OSI Approved :: GNU General Public License v3 or later (GPLv3+)
Requires-Dist: pandas
Requires-Dist: openai
Project-URL: Home, https://github.com/BardiaKh/RadPrompter
